[{"id":"bd0be6e5.ffc838","type":"shelly-rgbw2","z":"75aa2889.5e4d78","hostname":"192.168.178.178","description":"RGBW2","ledStat":true,"pollinginterval":"5000","mode":"white","x":500,"y":540,"wires":[["11433e35.876122"]]},{"id":"11433e35.876122","type":"debug","z":"75aa2889.5e4d78","name":"","active":true,"tosidebar":true,"console":false,"tostatus":false,"complete":"false","statusVal":"","statusType":"auto","x":670,"y":540,"wires":[]},{"id":"fafae5b.2e88b18","type":"function","z":"75aa2889.5e4d78","name":"white","func":"msg.payload =\n{\n    light : msg.light,\n    brightness : 100,\n    timer : 0,\n    on : msg.on\n}\nreturn msg;","outputs":1,"noerr":0,"initialize":"","finalize":"","x":330,"y":540,"wires":[["bd0be6e5.ffc838"]]},{"id":"1b289470.261b8c","type":"inject","z":"75aa2889.5e4d78","name":"Light 0 On","props":[{"p":"light","v":"0","vt":"num"},{"p":"on","v":"true","vt":"bool"}],"repeat":"","crontab":"","once":false,"onceDelay":0.1,"topic":"","x":140,"y":500,"wires":[["fafae5b.2e88b18"]]},{"id":"3aafb57.7697e4a","type":"inject","z":"75aa2889.5e4d78","name":"Light 0 Off","props":[{"p":"light","v":"0","vt":"num"},{"p":"on","v":"false","vt":"bool"}],"repeat":"","crontab":"","once":false,"onceDelay":0.1,"topic":"","x":140,"y":540,"wires":[["fafae5b.2e88b18"]]},{"id":"ac06b0cd.5863e","type":"inject","z":"75aa2889.5e4d78","name":"Light 1 On","props":[{"p":"light","v":"1","vt":"num"},{"p":"on","v":"true","vt":"bool"}],"repeat":"","crontab":"","once":false,"onceDelay":0.1,"topic":"","x":140,"y":580,"wires":[["fafae5b.2e88b18"]]},{"id":"1ac0f79a.9d8cf8","type":"inject","z":"75aa2889.5e4d78","name":"Light 1 Off","props":[{"p":"light","v":"1","vt":"num"},{"p":"on","v":"false","vt":"bool"}],"repeat":"","crontab":"","once":false,"onceDelay":0.1,"topic":"","x":140,"y":620,"wires":[["fafae5b.2e88b18"]]},{"id":"2f01dd34.608022","type":"inject","z":"75aa2889.5e4d78","name":"Light 2 On","props":[{"p":"light","v":"2","vt":"num"},{"p":"on","v":"true","vt":"bool"}],"repeat":"","crontab":"","once":false,"onceDelay":0.1,"topic":"","x":140,"y":660,"wires":[["fafae5b.2e88b18"]]},{"id":"145ffc44.293804","type":"inject","z":"75aa2889.5e4d78","name":"Light 2 Off","props":[{"p":"light","v":"2","vt":"num"},{"p":"on","v":"false","vt":"bool"}],"repeat":"","crontab":"","once":false,"onceDelay":0.1,"topic":"","x":140,"y":700,"wires":[["fafae5b.2e88b18"]]},{"id":"452ef8fd.9c5948","type":"inject","z":"75aa2889.5e4d78","name":"Light 3 On","props":[{"p":"light","v":"3","vt":"num"},{"p":"on","v":"true","vt":"bool"}],"repeat":"","crontab":"","once":false,"onceDelay":0.1,"topic":"","x":140,"y":740,"wires":[["fafae5b.2e88b18"]]},{"id":"78f7eae.f515f14","type":"inject","z":"75aa2889.5e4d78","name":"Light 3 Off","props":[{"p":"light","v":"3","vt":"num"},{"p":"on","v":"false","vt":"bool"}],"repeat":"","crontab":"","once":false,"onceDelay":0.1,"topic":"","x":140,"y":780,"wires":[["fafae5b.2e88b18"]]}]